nbdev/__init__.py
nbdev/_nbdev.py
nbdev/all.py
nbdev/clean.py
nbdev/cli.py
nbdev/export.py
nbdev/export2html.py
nbdev/imports.py
nbdev/merge.py
nbdev/nbdev_comments.py
nbdev/showdoc.py
nbdev/sync.py
nbdev/template.py
nbdev/test.py
nbdev/tutorial.py
nbdev/version.py
nbdev/templates/autogen.tpl
nbdev/templates/hide-md.tpl
nbdev/templates/hide.tpl
nbdev/templates/jekyll-md.tpl
nbdev/templates/jekyll.tpl
nbdev/templates/md.tpl
nbdev_steve-1.2.13.dist-info/LICENSE
nbdev_steve-1.2.13.dist-info/METADATA
nbdev_steve-1.2.13.dist-info/WHEEL
nbdev_steve-1.2.13.dist-info/entry_points.txt
nbdev_steve-1.2.13.dist-info/top_level.txt
nbdev_steve-1.2.13.dist-info/RECORD
