Metadata-Version: 2.1
Name: nbdev-steve
Version: 1.2.13
Summary: Writing a library entirely in notebooks
Home-page: https://github.com/fastai/nbdev_steve/tree/master/
Author: Steve de Peijper, using work of Sylvain Gugger and Jeremy Howard
Author-email: steve.depeijper@gmail.com
License: Apache Software License 2.0
Keywords: jupyter notebook
Classifier: Development Status :: 5 - Production/Stable
Classifier: Intended Audience :: Developers
Classifier: License :: OSI Approved :: Apache Software License
Classifier: Natural Language :: English
Classifier: Programming Language :: Python :: 3.7
Classifier: Programming Language :: Python :: 3.8
Classifier: Programming Language :: Python :: 3.9
Classifier: Programming Language :: Python :: 3.10
Requires-Python: >=3.7
License-File: LICENSE
Requires-Dist: pip
Requires-Dist: packaging
Requires-Dist: fastcore (>=1.4.1)
Requires-Dist: nbformat (>=4.4.0)
Requires-Dist: nbconvert (>=6.1)
Requires-Dist: pyyaml
Requires-Dist: jupyter
Requires-Dist: jupyter-client (<8)
Requires-Dist: ipykernel
Requires-Dist: ghapi
Requires-Dist: fastrelease
Requires-Dist: Jinja2
Provides-Extra: dev
